{
  "project_info": {
    "project_number": "1012054669156",
    "firebase_url": "https://project-1066840240253461094.firebaseio.com",
    "project_id": "project-1066840240253461094",
    "storage_bucket": "project-1066840240253461094.appspot.com"
  },
  "client": [
    {
      "client_info": {
        "mobilesdk_app_id": "1:1012054669156:android:c09d3cc6f22a5394",
        "android_client_info": {
          "package_name": "com.pathguide"
        }
      },
      "oauth_client": [
        {
          "client_id": "1012054669156-0ered92de35jsh73ucpjfrscor1vdndb.apps.googleusercontent.com",
          "client_type": 3
        }
      ],
      "api_key": [
        {
          "current_key": "AIzaSyBHIMnT9fy-VOvi0RCQuHgQEyIbp6Y9tRo"
        }
      ],
      "services": {
        "analytics_service": {
          "status": 1
        },
        "appinvite_service": {
          "status": 1,
          "other_platform_oauth_client": []
        },
        "ads_service": {
          "status": 2
        }
      }
    }
  ],
  "configuration_version": "1"
}